webmocket/__init__.py
webmocket/server.py
webmocket-0.1.0.dist-info/METADATA
webmocket-0.1.0.dist-info/WHEEL
webmocket-0.1.0.dist-info/top_level.txt
webmocket-0.1.0.dist-info/RECORD
