Metadata-Version: 2.1
Name: webmocket
Version: 0.1.0
Summary: Fake websocket server for websocket integration tests.
Home-page: https://github.com/ahmetkotan/webmocket
Author: ahmetkotan
Author-email: ahmtkotan@gmail.com
License: UNKNOWN
Platform: UNKNOWN
Classifier: Environment :: Web Environment
Classifier: Operating System :: OS Independent
Classifier: Framework :: AsyncIO
Classifier: Programming Language :: Python
Classifier: Programming Language :: Python :: 3
Classifier: Programming Language :: Python :: 3.8
Requires-Dist: asgiref (==3.3.4)
Requires-Dist: asyncio (==3.4.3)
Requires-Dist: websockets (==8.1)
